markdown_it_accel-0.1.0.dist-info/METADATA
markdown_it_accel-0.1.0.dist-info/WHEEL
markdown_it_accel-0.1.0.dist-info/licenses/LICENSE
markdown_it_accel/__init__.py
markdown_it_accel/_rust.abi3.so
markdown_it_accel/_rust.pyi
markdown_it_accel/_shim.py
markdown_it_accel/py.typed
markdown_it_accel-0.1.0.dist-info/RECORD
