Metadata-Version: 2.4
Name: markdown-it-accel
Version: 0.1.0
Classifier: Development Status :: 4 - Beta
Classifier: Intended Audience :: Developers
Classifier: License :: OSI Approved :: MIT License
Classifier: Operating System :: OS Independent
Classifier: Programming Language :: Python :: 3
Classifier: Programming Language :: Python :: 3.8
Classifier: Programming Language :: Python :: 3.9
Classifier: Programming Language :: Python :: 3.10
Classifier: Programming Language :: Python :: 3.11
Classifier: Programming Language :: Python :: 3.12
Classifier: Programming Language :: Python :: Implementation :: CPython
Classifier: Programming Language :: Rust
Classifier: Topic :: Internet :: WWW/HTTP :: Dynamic Content
Classifier: Topic :: Software Development :: Libraries :: Python Modules
Classifier: Topic :: Text Processing :: Markup
Classifier: Topic :: Text Processing :: Markup :: HTML
Classifier: Typing :: Typed
Requires-Dist: markdown-it-py>=3.0.0
Requires-Dist: pytest>=6.0 ; extra == 'dev'
Requires-Dist: pytest-benchmark ; extra == 'dev'
Requires-Dist: ruff ; extra == 'dev'
Requires-Dist: black ; extra == 'dev'
Requires-Dist: mypy ; extra == 'dev'
Requires-Dist: maturin ; extra == 'dev'
Requires-Dist: pytest-benchmark ; extra == 'benchmark'
Requires-Dist: markdown ; extra == 'benchmark'
Requires-Dist: mistune ; extra == 'benchmark'
Provides-Extra: dev
Provides-Extra: benchmark
License-File: LICENSE
Summary: Rust-accelerated backend for markdown-it-py with 50-200x performance improvements
Keywords: markdown,rust,acceleration,performance,pulldown-cmark,commonmark,gfm
Author-email: ChungNYCU <chungncu@gmail.com>
Maintainer-email: ChungNYCU <chungncu@gmail.com>
Requires-Python: >=3.8
Project-URL: Homepage, https://github.com/ChungNYCU/markdown-it-accel
Project-URL: Repository, https://github.com/ChungNYCU/markdown-it-accel.git
Project-URL: Issues, https://github.com/ChungNYCU/markdown-it-accel/issues
Project-URL: Documentation, https://github.com/ChungNYCU/markdown-it-accel#readme
Project-URL: Changelog, https://github.com/ChungNYCU/markdown-it-accel#changelog
